{
  "collection": "FAST_DOCS",
  "status": "SUCCESS",
  "chunks_loaded": {
    "collections_loaded": 3,
    "total_chunks_loaded": 329,
    "chunks_by_collection": {
      "modelcontextprotocol_python-sdk": 130,
      "fastapi_fastapi": 127,
      "jlowin_fastmcp": 72
    },
    "loading_errors": [],
    "memory_usage_mb": 1634.796875,
    "preprocessing_stats": {
      "cache_size": 316,
      "hit_count": 13,
      "miss_count": 316,
      "hit_rate": 0.03951367781155015,
      "memory_mb": 1.0396795272827148
    }
  },
  "embedding_results": {
    "total_embeddings_generated": 329,
    "embedding_dimension": 768,
    "processing_time_seconds": 2.0009517669677734,
    "chunks_per_second": 164.4217544026881,
    "gpu_count": 2,
    "optimal_batch_size": 64,
    "total_batches": 3,
    "model_used": "nomic-coderank",
    "backend": "pytorch",
    "precision": "fp16",
    "embedding_memory_mb": 0.9638671875,
    "memory_per_chunk_kb": 3.0,
    "kaggle_optimized": true,
    "performance_stats": {
      "gpu_memory": [
        {
          "gpu_id": 0,
          "memory_used_gb": 0.280061952,
          "memory_reserved_gb": 0.438304768,
          "memory_total_gb": 15.828320256,
          "utilization_percent": 1.769372539033873,
          "timestamp": 1760642573.962576
        },
        {
          "gpu_id": 1,
          "memory_used_gb": 0.0,
          "memory_reserved_gb": 0.0,
          "memory_total_gb": 15.828320256,
          "utilization_percent": 0.0,
          "timestamp": 1760642573.9628236
        }
      ],
      "system_metrics": [
        {
          "cpu_percent": 0.0,
          "memory_used_gb": 2.707509248,
          "memory_percent": 8.0,
          "timestamp": 1760642573.963605
        }
      ]
    }
  },
  "export_files": {
    "numpy": "/kaggle/working/FAST_DOCS_v4_embeddings.npy",
    "jsonl": "/kaggle/working/FAST_DOCS_v4_qdrant.jsonl",
    "faiss": "/kaggle/working/FAST_DOCS_v4_index.faiss",
    "metadata": "/kaggle/working/FAST_DOCS_v4_metadata.json",
    "texts": "/kaggle/working/FAST_DOCS_v4_texts.json",
    "stats": "/kaggle/working/FAST_DOCS_v4_stats.json",
    "upload_script": "/kaggle/working/FAST_DOCS_v4_upload_script.py"
  },
  "processing_time_seconds": 9.191056251525879,
  "timestamp": "2025-10-16T19:22:56.179443"
}