{
  "kaggle_environment": true,
  "model_config": {
    "name": "nomic-coderank",
    "hf_model_id": "nomic-ai/CodeRankEmbed",
    "vector_dimension": 768,
    "max_tokens": 2048
  },
  "gpu_config": {
    "device_count": 2,
    "backend": "pytorch",
    "precision": "fp16",
    "total_vram_gb": 31.66
  },
  "embedding_stats": {
    "total_embeddings": 40,
    "embedding_dimension": 1024,
    "memory_usage_mb": 0.15625
  },
  "processing_performance": {
    "gpu_memory": [
      {
        "gpu_id": 0,
        "memory_used_gb": 1.421310976,
        "memory_reserved_gb": 2.562719744,
        "memory_total_gb": 15.828320256,
        "utilization_percent": 8.979543963050832,
        "timestamp": 1760880885.980469
      },
      {
        "gpu_id": 1,
        "memory_used_gb": 0.0,
        "memory_reserved_gb": 0.0,
        "memory_total_gb": 15.828320256,
        "utilization_percent": 0.0,
        "timestamp": 1760880885.9806633
      },
      {
        "gpu_id": 0,
        "memory_used_gb": 1.616449536,
        "memory_reserved_gb": 4.09993216,
        "memory_total_gb": 15.828320256,
        "utilization_percent": 10.212388363744768,
        "timestamp": 1760880887.983231
      },
      {
        "gpu_id": 1,
        "memory_used_gb": 0.0,
        "memory_reserved_gb": 0.0,
        "memory_total_gb": 15.828320256,
        "utilization_percent": 0.0,
        "timestamp": 1760880887.9834352
      }
    ],
    "system_metrics": [
      {
        "cpu_percent": 18.8,
        "memory_used_gb": 6.251016192,
        "memory_percent": 18.6,
        "timestamp": 1760880885.982705
      },
      {
        "cpu_percent": 26.3,
        "memory_used_gb": 6.251016192,
        "memory_percent": 18.6,
        "timestamp": 1760880887.9836626
      }
    ]
  },
  "export_timestamp": "2025-10-19T13:34:50.032322",
  "sparse_vector_stats": {
    "total_chunks": 40,
    "sparse_vectors_available": 40,
    "coverage_ratio": 1.0
  },
  "preprocessing_cache": {
    "cache_size": 38,
    "hit_count": 2,
    "miss_count": 38,
    "hit_rate": 0.05,
    "memory_mb": 0.03722572326660156
  }
}